tests/__init__.py
tests/test_tokenizers.py
tests/test_transducers.py
yakutmorph/__init__.py
yakutmorph/disambiguation.py
yakutmorph/interfaces.py
yakutmorph/main.py
yakutmorph/mappers.py
yakutmorph/tokenizers.py
yakutmorph/transducers.py
yakutmorph/utils.py
yakutmorph/wrappers.py
yakutmorph/data/__init__.py
yakutmorph/data/gru_weights.pth
yakutmorph/data/mappings.pkl
yakutmorph/data/mappings.yaml
yakutmorph/data/morph_reference.yaml
yakutmorph/data/validate_structure.py
yakutmorph/data/vocabulary.pkl
yakutmorph/fsts/__init__.py
yakutmorph/fsts/yma.a
yakutmorph/fsts/yms.a
yakutmorph/fsts/ymv.a
yakutmorph-0.0.5.dist-info/LICENSE
yakutmorph-0.0.5.dist-info/METADATA
yakutmorph-0.0.5.dist-info/WHEEL
yakutmorph-0.0.5.dist-info/top_level.txt
yakutmorph-0.0.5.dist-info/RECORD
