Metadata-Version: 2.1
Name: yakutmorph
Version: 0.0.5
Summary: A morphological analyzer for Yakut language
Home-page: https://github.com/nicolascortegoso/yakutmorph
Author: Nicolas Cortegoso Vissio
Author-email: Nicolas Cortegoso Vissio <nicolascortegoso@hotmail.com>
Keywords: python,morphology,analyzer,Yakut,Sakha,NLP
Classifier: Development Status :: 1 - Planning
Classifier: Intended Audience :: Developers
Classifier: License :: OSI Approved :: GNU General Public License v3 (GPLv3)
Classifier: Programming Language :: Python :: 3
Classifier: Operating System :: Unix
Classifier: Operating System :: MacOS :: MacOS X
Classifier: Operating System :: Microsoft :: Windows
Requires-Python: >=3.8
License-File: LICENSE
Requires-Dist: sfst-transduce (>=1.0.2)
Requires-Dist: torch (>=1.10.0)
Requires-Dist: PyYAML (>=6.0.1)
